ensure_packages/__init__.py
ensure_packages/ensure_package.py
ensure_packages-0.1.5.dist-info/METADATA
ensure_packages-0.1.5.dist-info/WHEEL
ensure_packages-0.1.5.dist-info/top_level.txt
ensure_packages-0.1.5.dist-info/RECORD
